check_iso8601_version_string.py
check_iso8601_version_string-2023.12.20.dist-info/LICENSE
check_iso8601_version_string-2023.12.20.dist-info/METADATA
check_iso8601_version_string-2023.12.20.dist-info/WHEEL
check_iso8601_version_string-2023.12.20.dist-info/entry_points.txt
check_iso8601_version_string-2023.12.20.dist-info/top_level.txt
check_iso8601_version_string-2023.12.20.dist-info/RECORD
