Metadata-Version: 2.1
Name: check_iso8601_version_string
Version: 2023.12.20
Summary: Tool for checking that an ISO 8601 version string (in `__version__`) is valid and set to today's date
Home-page: https://github.com/simonrob/check-iso8601-version-string
Author: Simon Robinson
Author-email: simon@robinson.ac
License: Apache License 2.0
Classifier: License :: OSI Approved :: Apache Software License
Requires-Python: >=3.6
License-File: LICENSE
